setup.py
ranyou_distributions/Binomialdistribution.py
ranyou_distributions/Gaussiandistribution.py
ranyou_distributions/Generaldistribution.py
ranyou_distributions/__init__.py
ranyou_distributions.egg-info/PKG-INFO
ranyou_distributions.egg-info/SOURCES.txt
ranyou_distributions.egg-info/dependency_links.txt
ranyou_distributions.egg-info/not-zip-safe
ranyou_distributions.egg-info/top_level.txt