Metadata-Version: 1.0
Name: ranyou-distributions
Version: 0.1
Summary: Gaussian and Binomial distributions
Home-page: UNKNOWN
Author: Ran You
Author-email: iamranyou@gmail.com
License: UNKNOWN
Platform: UNKNOWN
